github_asset.py
github_asset-0.1.3.dist-info/METADATA
github_asset-0.1.3.dist-info/WHEEL
github_asset-0.1.3.dist-info/entry_points.txt
github_asset-0.1.3.dist-info/top_level.txt
github_asset-0.1.3.dist-info/RECORD
