Metadata-Version: 2.1
Name: github-asset
Version: 0.1.3
Summary: UNKNOWN
Home-page: UNKNOWN
License: UNKNOWN
Platform: UNKNOWN
Requires-Python: >=3.6
Requires-Dist: fire
Requires-Dist: requests
Requires-Dist: tqdm
